arbytmap/CHANGELOG.MD
arbytmap/LICENSE.TXT
arbytmap/README.md
arbytmap/__init__.py
arbytmap/arby.py
arbytmap/bitmap_io.py
arbytmap/constants.py
arbytmap/dds_defs.py
arbytmap/format_defs.py
arbytmap/swizzler.py
arbytmap/test.py
arbytmap/tiler.py
arbytmap/ext/__init__.py
arbytmap/ext/arbytmap_ext.cp36-win_amd64.pyd
arbytmap/ext/bitmap_io_ext.cp36-win_amd64.pyd
arbytmap/ext/dds_defs_ext.cp36-win_amd64.pyd
arbytmap/ext/raw_packer_ext.cp36-win_amd64.pyd
arbytmap/ext/raw_unpacker_ext.cp36-win_amd64.pyd
arbytmap/ext/swizzler_ext.cp36-win_amd64.pyd
arbytmap/src/arbytmap_ext.c
arbytmap/src/bitmap_io_ext.c
arbytmap/src/dds_defs_ext.c
arbytmap/src/raw_packer_ext.c
arbytmap/src/raw_unpacker_ext.c
arbytmap/src/shared.h
arbytmap/src/swizzler_ext.c
arbytmap/src/tiler_ext.c
arbytmap-1.1.2.dist-info/LICENSE.TXT
arbytmap-1.1.2.dist-info/METADATA
arbytmap-1.1.2.dist-info/WHEEL
arbytmap-1.1.2.dist-info/top_level.txt
arbytmap-1.1.2.dist-info/RECORD
