Metadata-Version: 2.1
Name: arbytmap
Version: 1.1.2
Summary: A texture manipulation module for python 3.
Home-page: https://github.com/Sigmmma/arbytmap
Author: Devin Bobadilla
Author-email: MosesBobadilla@gmail.com
License: MIT
Keywords: arbytmap,texture,bitmap,converter,image,editing
Platform: POSIX
Platform: Windows
Classifier: Development Status :: 4 - Beta
Classifier: Intended Audience :: Developers
Classifier: License :: OSI Approved :: MIT License
Classifier: Programming Language :: Python
Classifier: Programming Language :: Python :: 3
Classifier: Programming Language :: Python :: 3.5
Classifier: Programming Language :: Python :: 3.6
Classifier: Programming Language :: Python :: 3.7
Classifier: Programming Language :: Python :: 3.8
Classifier: Programming Language :: Python :: 3.9
Classifier: Programming Language :: Python :: 3 :: Only
Classifier: Topic :: Multimedia :: Graphics :: Graphics Conversion
Classifier: Programming Language :: C
Provides: arbytmap
